{
  "heroes": [
    {
      "id": "b5f782f3-db58-4b2d-b943-df08c838e233",
      "name": "Аанг",
      "description": "Аватар, последний маг воздуха",
      "element": "air"
    },
    {
      "id": "05674ead-d64b-4684-876e-e1fa69258ab4",
      "name": "Зуко",
      "description": "Маг огня, император Страны Огня",
      "element": "fire"
    },
    {
      "id": "8efcf9b8-0929-4fa0-9ffb-9d1f03f0d48a",
      "name": "Катара",
      "description": "Маг племени воды",
      "element": "water"
    },
    {
      "id": "53f757eb-5da3-4d87-ab94-fa34f6c798fb",
      "name": "Тофф",
      "description": "Маг земли, слепой воин",
      "element": "earth"
    }
  ],
  "filters": [
    {
      "id": "all",
      "name": "all",
      "label": "Все",
      "className": "btn-outline-dark"
    },
    {
      "id": "fire",
      "name": "fire",
      "label": "Огонь",
      "className": "btn-danger"
    },
    {
      "id": "water",
      "name": "water",
      "label": "Вода",
      "className": "btn-primary"
    },
    {
      "id": "air",
      "name": "air",
      "label": "Воздух",
      "className": "btn-success"
    },
    {
      "id": "earth",
      "name": "earth",
      "label": "Земля",
      "className": "btn-secondary"
    }
  ]
}